README.rst
setup.py
UnPackIps/UnPackIps.py
UnPackIps/__init__.py
UnpackIPs.egg-info/PKG-INFO
UnpackIPs.egg-info/SOURCES.txt
UnpackIPs.egg-info/dependency_links.txt
UnpackIPs.egg-info/requires.txt
UnpackIPs.egg-info/top_level.txt