Metadata-Version: 2.1
Name: UnpackIPs
Version: 2.0.2
Summary: Allow a user to unpack IP ranges
Home-page: https://github.com/cober2019/UnpackIPs
Author: cober2019
Author-email: cober91130@gmail.com
License: UNKNOWN
Platform: UNKNOWN
Classifier: Programming Language :: Python :: 3
Classifier: License :: OSI Approved :: MIT License
Classifier: Operating System :: OS Independent
Requires-Python: >=3.6
